sepunycoder/__init__.py
sepunycoder/main.py
sepunycoder/punycode_chars.json
sepunycoder-3.0.0.dist-info/LICENSE
sepunycoder-3.0.0.dist-info/METADATA
sepunycoder-3.0.0.dist-info/WHEEL
sepunycoder-3.0.0.dist-info/entry_points.txt
sepunycoder-3.0.0.dist-info/top_level.txt
sepunycoder-3.0.0.dist-info/RECORD
