Metadata-Version: 2.1
Name: sepunycoder
Version: 3.0.0
Summary: A simple script to convert normal-text to Cyrillic-text. This allows hackers to obfuscate text in puny-code format which can lead into a lot of multiple Phishing attacks.
Home-page: https://github.com/mateofumis/SEPunycoder.py
Author: Mateo Fumis
Author-email: mateofumis1@gmail.com
Classifier: Programming Language :: Python :: 3
Classifier: License :: OSI Approved :: MIT License
Classifier: Operating System :: OS Independent
Requires-Python: >=3.6
License-File: LICENSE
